iroiro/__init__.py
iroiro/__main__.py
iroiro/bin_iroiro.py
iroiro/bin_ntfy.py
iroiro/bin_palette.py
iroiro/bin_rainbow.py
iroiro/bin_sponge.py
iroiro/internal_utils.py
iroiro/lib_colors.py
iroiro/lib_fs.py
iroiro/lib_itertools.py
iroiro/lib_math.py
iroiro/lib_regex.py
iroiro/lib_sh.py
iroiro/lib_subproc.py
iroiro/lib_test_utils.py
iroiro/lib_tui.py
iroiro/test_bin_iroiro.py
iroiro/test_colors.py
iroiro/test_fs.py
iroiro/test_internal_utils.py
iroiro/test_itertools.py
iroiro/test_math.py
iroiro/test_regex.py
iroiro/test_sh.py
iroiro/test_subproc.py
iroiro/test_test_utils.py
iroiro/test_tui.py
iroiro/bin/__init__.py
iroiro-0.2.2.dist-info/METADATA
iroiro-0.2.2.dist-info/WHEEL
iroiro-0.2.2.dist-info/entry_points.txt
iroiro-0.2.2.dist-info/licenses/LICENSE
iroiro-0.2.2.dist-info/RECORD
