Metadata-Version: 2.4
Name: iroiro
Version: 0.2.2
Summary: Some cute utilties for my other projects
Project-URL: Homepage, https://github.com/pi314/iroiro
Author-email: Cychih <michael66230@gmail.com>
License-File: LICENSE
Classifier: Development Status :: 3 - Alpha
Classifier: Environment :: Console
Classifier: Intended Audience :: End Users/Desktop
Classifier: License :: OSI Approved :: BSD License
Classifier: Natural Language :: English
Classifier: Operating System :: MacOS :: MacOS X
Classifier: Programming Language :: Python :: 3
Classifier: Topic :: Utilities
Requires-Python: >=3.7
